kands/__init__.py
kands/kands.py
kands/main.py
kands-1.0.0.dist-info/entry_points.txt
kands-1.0.0.dist-info/WHEEL
kands-1.0.0.dist-info/METADATA
kands-1.0.0.dist-info/RECORD
