Metadata-Version: 2.1
Name: kands
Version: 1.0.0
Summary: Just a joke to give to a couple of friends a wedding surprise 👰🤵
Home-page: https://marcosgabarda.com
License: UNKNOWN
Author: Marcos Gabarda
Author-email: hey@marcosgabarda.com
Requires-Python: >=3.6
Classifier: License :: OSI Approved :: MIT License
Classifier: Topic :: Utilities
Requires-Dist: termcolor
